tests/__init__.py
tests/test_covid_data_handler.py
tests/test_logger.py
tests/test_news_data_handling.py
tests/test_shared_functions.py
covid_19_dashboard_pkg_jwh220-0.0.1.dist-info/LICENSE
covid_19_dashboard_pkg_jwh220-0.0.1.dist-info/METADATA
covid_19_dashboard_pkg_jwh220-0.0.1.dist-info/WHEEL
covid_19_dashboard_pkg_jwh220-0.0.1.dist-info/top_level.txt
covid_19_dashboard_pkg_jwh220-0.0.1.dist-info/RECORD
