Metadata-Version: 2.1
Name: covid-19-dashboard-pkg-jwh220
Version: 0.0.1
Summary: Covid-19 online dashboard.
Home-page: https://github.com/Peter-Bread/CS-Programming-Module-Current
Author: Joshua Hammond
Author-email: jwh220@exeter.ac.uk
License: UNKNOWN
Platform: UNKNOWN
Classifier: Programming Language :: Python :: 3
Classifier: License :: OSI Approved :: MIT License
Classifier: Operating System :: OS Independent
Requires-Python: >=3.10
